otargenpy/__init__.py
otargenpy/otargenpy.py
otargenpy/query.py
otargenpy-0.2.1.dist-info/AUTHORS.rst
otargenpy-0.2.1.dist-info/LICENSE
otargenpy-0.2.1.dist-info/METADATA
otargenpy-0.2.1.dist-info/WHEEL
otargenpy-0.2.1.dist-info/top_level.txt
otargenpy-0.2.1.dist-info/RECORD
