Metadata-Version: 2.1
Name: otargenpy
Version: 0.2.1
Summary: Interact seamlessly with Open Target Genetics' GraphQL endpoint to query and retrieve tidy data tables, facilitating the analysis of genetic data
Home-page: https://github.com/amirfeizi/otargenpy/
Author: Amir Feizi
Author-email: afeizi@gmail.com
License: MIT license
Keywords: otargenpy
Classifier: Development Status :: 2 - Pre-Alpha
Classifier: Intended Audience :: Developers
Classifier: License :: OSI Approved :: MIT License
Classifier: Natural Language :: English
Classifier: Programming Language :: Python :: 3
Classifier: Programming Language :: Python :: 3.6
Classifier: Programming Language :: Python :: 3.7
Classifier: Programming Language :: Python :: 3.8
Requires-Python: >=3.6
License-File: LICENSE
License-File: AUTHORS.rst
Requires-Dist: requests
Requires-Dist: pandas
Requires-Dist: matplotlib
Requires-Dist: seaborn
Requires-Dist: numpy
